README.rst
setup.py
k2mosaic/__init__.py
k2mosaic/mast.py
k2mosaic/mosaic.py
k2mosaic/movie.py
k2mosaic/ui.py
k2mosaic/version.py
k2mosaic.egg-info/PKG-INFO
k2mosaic.egg-info/SOURCES.txt
k2mosaic.egg-info/dependency_links.txt
k2mosaic.egg-info/entry_points.txt
k2mosaic.egg-info/requires.txt
k2mosaic.egg-info/top_level.txt
k2mosaic/data/k2-ffi-headers.csv