Metadata-Version: 1.1
Name: k2mosaic
Version: 3.0.2
Summary: Mosaic Target Pixel Files (TPFs) obtained by NASA's Kepler/K2 missions into CCD-sized images and movies.
Home-page: https://k2mosaic.geert.io
Author: Geert Barentsen
Author-email: hello@geert.io
License: MIT
Platform: UNKNOWN
Classifier: Development Status :: 5 - Production/Stable
Classifier: License :: OSI Approved :: MIT License
Classifier: Operating System :: OS Independent
Classifier: Programming Language :: Python :: 2.7
Classifier: Programming Language :: Python :: 3
Classifier: Intended Audience :: Science/Research
Classifier: Topic :: Scientific/Engineering :: Astronomy
